{
  "total_episodes": 733,
  "epoch": 2,
  "epoch_episode": 233,
  "question_number": 8,
  "topic": "ds",
  "subtopic": "Arrays",
  "difficulty": 1.98,
  "performance": 0.19352476063764398,
  "time_taken": 8.968208400522615,
  "actor_loss": -0.0007734600057894934,
  "value_loss": 28.433198256623655,
  "entropy_loss": -0.0012876820883489448,
  "topic_means": {
    "ds": 0.0,
    "algo": 0.0,
    "oops": 0.0,
    "dbms": 0.0,
    "os": 0.0,
    "cn": 0.0,
    "system_design": 0.0
  },
  "consecutive_low_scores": 0,
  "safety_constraints_applied": false
}